cqueue/__init__.py
cqueue-1.1.2.dist-info/LICENSE
cqueue-1.1.2.dist-info/METADATA
cqueue-1.1.2.dist-info/WHEEL
cqueue-1.1.2.dist-info/top_level.txt
cqueue-1.1.2.dist-info/RECORD
