Metadata-Version: 2.1
Name: cqueue
Version: 1.1.2
Summary: Sophisticate Circular Queue
Home-page: https://pypi.org/project/cqueue/
Author: khiat Mohammed Abderrezzak
Author-email: khiat.dev@gmail.com
License: MIT
Keywords: circular queue
Classifier: Programming Language :: Python :: 3
Classifier: Operating System :: OS Independent
Classifier: License :: OSI Approved :: MIT License
Requires-Python: >=3.6
License-File: LICENSE
Requires-Dist: linkedit (>=1.1.3)
